Metadata-Version: 1.1
Name: elastic-check
Version: 0.1
Summary: Elastic cluster monitoring script
Home-page: https://github.com/rennym19/elastic-check
Author: Renny Montero
Author-email: rennym19@gmail.com
License: MIT
Download-URL: https://github.com/rennym19/elastic-check/archive/v_0_1.tar.gz
Keywords: ELASTIC,SEARCH,CLUSTER,MONIT,MONITOR,CHECK
Platform: UNKNOWN
Classifier: Development Status :: 4 - Beta
Classifier: Intended Audience :: Developers
Classifier: Topic :: Software Development :: Build Tools
Classifier: License :: OSI Approved :: MIT License
Classifier: Programming Language :: Python :: 3
Classifier: Programming Language :: Python :: 3.4
Classifier: Programming Language :: Python :: 3.5
Classifier: Programming Language :: Python :: 3.6
Classifier: Programming Language :: Python :: 3.7
Classifier: Programming Language :: Python :: 3.8
Classifier: Programming Language :: Python :: 3.9
